jupyterlab_quickopen/__init__.py
jupyterlab_quickopen/_version.py
jupyterlab_quickopen/handler.py
jupyterlab_quickopen-2.1.0.data/data/etc/jupyter/jupyter_server_config.d/jupyterlab_quickopen.json
jupyterlab_quickopen-2.1.0.data/data/share/jupyter/labextensions/jupyterlab-quickopen/package.json
jupyterlab_quickopen-2.1.0.data/data/share/jupyter/labextensions/jupyterlab-quickopen/schemas/jupyterlab-quickopen/package.json.orig
jupyterlab_quickopen-2.1.0.data/data/share/jupyter/labextensions/jupyterlab-quickopen/schemas/jupyterlab-quickopen/plugin.json
jupyterlab_quickopen-2.1.0.data/data/share/jupyter/labextensions/jupyterlab-quickopen/static/339.36214c4e67ebce3c3d51.js
jupyterlab_quickopen-2.1.0.data/data/share/jupyter/labextensions/jupyterlab-quickopen/static/728.76baab422b4b296033a5.js
jupyterlab_quickopen-2.1.0.data/data/share/jupyter/labextensions/jupyterlab-quickopen/static/remoteEntry.7dbdcef52330783ea224.js
jupyterlab_quickopen-2.1.0.data/data/share/jupyter/labextensions/jupyterlab-quickopen/static/style.js
jupyterlab_quickopen-2.1.0.data/data/share/jupyter/labextensions/jupyterlab-quickopen/static/third-party-licenses.json
jupyterlab_quickopen-2.1.0.data/data/share/jupyter/labextensions/jupyterlab-quickopen/install.json
jupyterlab_quickopen-2.1.0.dist-info/METADATA
jupyterlab_quickopen-2.1.0.dist-info/WHEEL
jupyterlab_quickopen-2.1.0.dist-info/licenses/LICENSE
jupyterlab_quickopen-2.1.0.dist-info/RECORD
