Metadata-Version: 2.4
Name: jupyterlab-quickopen
Version: 2.1.0
Summary: Quickly open a file in JupyterLab by part of its name
Project-URL: Homepage, https://github.com/jupyterlab-contrib/jupyterlab-quickopen
Project-URL: Bug Tracker, https://github.com/jupyterlab-contrib/jupyterlab-quickopen/issues
Project-URL: Repository, https://github.com/jupyterlab-contrib/jupyterlab-quickopen.git
Author: JupyterLab Contrib Team
License: Copyright (c) 2018, 2020 Peter Parente
License-File: LICENSE
Keywords: jupyter,jupyterlab,jupyterlab-extension
Classifier: Framework :: Jupyter
Classifier: Framework :: Jupyter :: JupyterLab
Classifier: Framework :: Jupyter :: JupyterLab :: 4
Classifier: Framework :: Jupyter :: JupyterLab :: Extensions
Classifier: Framework :: Jupyter :: JupyterLab :: Extensions :: Prebuilt
Classifier: License :: OSI Approved :: BSD License
Classifier: Programming Language :: Python
Classifier: Programming Language :: Python :: 3
Classifier: Programming Language :: Python :: 3.8
Classifier: Programming Language :: Python :: 3.9
Classifier: Programming Language :: Python :: 3.10
Classifier: Programming Language :: Python :: 3.11
Classifier: Programming Language :: Python :: 3.12
Requires-Python: >=3.8
Requires-Dist: jupyter-server<3,>=2.4.2
